jax_fem/README.md
jax_fem/__init__.py
jax_fem/basis.py
jax_fem/fe.py
jax_fem/generate_mesh.py
jax_fem/logger_setup.py
jax_fem/mma.py
jax_fem/problem.py
jax_fem/solver.py
jax_fem/utils.py
jax_fem/experimental/adjoint_save_to_local.py
jax_fem/experimental/autodiff_utils.py
jax_fem/experimental/custom_jvp.py
jax_fem/experimental/jit_global.py
jax_fem/experimental/lm_solver.py
jax_fem/experimental/memory.py
jax_fem/experimental/petsc_solver.py
jax_fem/experimental/safe_grad.py
jax_fem/experimental/sparse.py
jax_fem/experimental/when_to_jit.py
jax_fem-0.0.11.dist-info/METADATA
jax_fem-0.0.11.dist-info/WHEEL
jax_fem-0.0.11.dist-info/licenses/LICENSE
jax_fem-0.0.11.dist-info/RECORD
