Metadata-Version: 2.3
Name: jax-fem
Version: 0.0.11
Summary: A GPU accelerated Finite element analysis package in JAX.
Author-email: Tianju Xue <cetxue@ust.hk>, Weipeng Xu <wxuby@connect.ust.hk>
License:                     GNU GENERAL PUBLIC LICENSE
Keywords: Differentiable programming,Finite element analysis,GPU,JAX,Python
Classifier: Intended Audience :: Science/Research
Classifier: License :: OSI Approved :: BSD License
Classifier: Natural Language :: English
Classifier: Programming Language :: Python :: 3
Classifier: Topic :: Scientific/Engineering
Classifier: Topic :: Scientific/Engineering :: Artificial Intelligence
Classifier: Topic :: Scientific/Engineering :: Physics
Requires-Python: >=3.9
